[
    {
        "Word": "דֶּשֶׁא",
        "Shoresh": "דֶּשֶׁא"
    },
    {
        "Word": "דֶּרֶךְ",
        "Shoresh": "דֶּרֶךְ"
    },
    {
        "Word": "דְּמֵי",
        "Shoresh": "דְּמֵיI"
    },
    {
        "Word": "דַּרְכּוֹ",
        "Shoresh": "דֶּ֫רֶךְ"
    },
    {
        "Word": "דְּגֵי",
        "Shoresh": "דָּאג"
    },
    {
        "Word": "דָמוֹ",
        "Shoresh": "דָּם"
    },
    {
        "Word": "דִּמְכֶם",
        "Shoresh": "דָּם"
    },
    {
        "Word": "דַּם",
        "Shoresh": "דָּם"
    },
    {
        "Word": "דָּמוֹ",
        "Shoresh": "דָּם"
    },
    {
        "Word": "דִּקְלָֽה",
        "Shoresh": "דִּקְלָה"
    },
    {
        "Word": "דִּבֶּר",
        "Shoresh": "דָּבַר"
    },
    {
        "Word": "דְּבַר",
        "Shoresh": "דְּבַר"
    },
    {
        "Word": "דָּֽן",
        "Shoresh": "דִּין"
    },
    {
        "Word": "דְבַר",
        "Shoresh": "דָּבָר"
    },
    {
        "Word": "דַּמֶּשֶׂק",
        "Shoresh": "דַּמֶּשֶׂק"
    },
    {
        "Word": "דָּן",
        "Shoresh": "דִּין"
    },
    {
        "Word": "דִּבַּֽרְתָּ",
        "Shoresh": "דָּבַר"
    },
    {
        "Word": "דָּבָר",
        "Shoresh": "דָּבָר"
    },
    {
        "Word": "דָבָר",
        "Shoresh": "דָּבָר"
    },
    {
        "Word": "דַּע",
        "Shoresh": "יְדַע"
    },
    {
        "Word": "דִּבֵּֽר",
        "Shoresh": "דָּבַר"
    },
    {
        "Word": "דִּבְרֵי",
        "Shoresh": "דָּבָר"
    },
    {
        "Word": "דִבֶּר",
        "Shoresh": "דָּבַר"
    },
    {
        "Word": "דִּבַּרְתִּי",
        "Shoresh": "דָּבַר"
    },
    {
        "Word": "דְּבָרָי",
        "Shoresh": "דָּבָר"
    },
    {
        "Word": "דַּבֵּֽר",
        "Shoresh": "דָּבַר"
    },
    {
        "Word": "דַּרְכֶּךָ",
        "Shoresh": "דֶּ֫רֶךְ"
    },
    {
        "Word": "דַּרְכִּי",
        "Shoresh": "דֶּ֫רֶךְ"
    },
    {
        "Word": "דַּבֵּר",
        "Shoresh": "דָּבַר"
    },
    {
        "Word": "דִּבְרֵיהֶם",
        "Shoresh": "דָּבָר"
    },
    {
        "Word": "דְּדָן",
        "Shoresh": "דְּדָן"
    },
    {
        "Word": "דְדָן",
        "Shoresh": "דְּדָן"
    },
    {
        "Word": "דִּבַּרְתָּ",
        "Shoresh": "דָּבַר"
    },
    {
        "Word": "דָּגָן",
        "Shoresh": "דָּגָן"
    },
    {
        "Word": "דָּנַנִּי",
        "Shoresh": "דִּין"
    },
    {
        "Word": "דֽוּדָאִים",
        "Shoresh": "דּוּדַי"
    },
    {
        "Word": "דּוּדָאֵי",
        "Shoresh": "דּוּדַי"
    },
    {
        "Word": "דִּינָֽה",
        "Shoresh": "דִּין"
    },
    {
        "Word": "דֶרֶךְ",
        "Shoresh": "דֶּ֫רֶךְ"
    },
    {
        "Word": "דָלַקְתָּ",
        "Shoresh": "דָּלַק"
    },
    {
        "Word": "דִינָה",
        "Shoresh": "דִּינָה"
    },
    {
        "Word": "דִּינָה",
        "Shoresh": "דִּין"
    },
    {
        "Word": "דִבְרֵיהֶם",
        "Shoresh": "דָּבָר"
    },
    {
        "Word": "דְּבֹרָה",
        "Shoresh": "דְּבוֹרָה"
    },
    {
        "Word": "דִּשֹׁן",
        "Shoresh": ""
    },
    {
        "Word": "דִישָׁן",
        "Shoresh": "דִּישָׁן"
    },
    {
        "Word": "דִּישָׁן",
        "Shoresh": "דִּישָׁן"
    },
    {
        "Word": "דִּנְהָֽבָה",
        "Shoresh": "דִּנְהָ֑בָה"
    },
    {
        "Word": "דִּבָּתָם",
        "Shoresh": "דִּבָּה"
    },
    {
        "Word": "דַּבְּרוֹ",
        "Shoresh": "דָּבַר"
    },
    {
        "Word": "דְּבָרָֽיו",
        "Shoresh": "דָּבָר"
    },
    {
        "Word": "דֹּתָיְנָה",
        "Shoresh": "דֹּתָן"
    },
    {
        "Word": "דָם",
        "Shoresh": "דָּם"
    },
    {
        "Word": "דָּמֽוֹ",
        "Shoresh": "דָּם"
    },
    {
        "Word": "דִּבְּרָה",
        "Shoresh": "דִּבְּרָה"
    },
    {
        "Word": "דַּקּוֹת",
        "Shoresh": "דַּקI"
    },
    {
        "Word": "דַּלּוֹת",
        "Shoresh": "דַּלָּה"
    },
    {
        "Word": "דִּבְרֵיכֶם",
        "Shoresh": "דָּבָר"
    },
    {
        "Word": "דִבְרֵיכֶם",
        "Shoresh": "דָּבָר"
    },
    {
        "Word": "דְּבַשׁ",
        "Shoresh": "דְּבַשׁ"
    },
    {
        "Word": "דִּבְּרוּ",
        "Shoresh": "דָּבַר"
    },
    {
        "Word": "דָן",
        "Shoresh": "ארנבן"
    },
    {
        "Word": "דַּבְּרוּ",
        "Shoresh": "דָּבַר"
    },
    {
        "Word": "דָּלֹה",
        "Shoresh": "דָּלָה"
    },
    {
        "Word": "דָלָה",
        "Shoresh": "דָּלָה"
    },
    {
        "Word": "דֹּֽר",
        "Shoresh": "דּוֹר"
    },
    {
        "Word": "דְּבָרִים",
        "Shoresh": "דָּבָר"
    },
    {
        "Word": "דַּבֶּרְךָ",
        "Shoresh": "דָּבַר"
    },
    {
        "Word": "דַבֵּר",
        "Shoresh": "דָּבַר"
    },
    {
        "Word": "דָּמִים",
        "Shoresh": "דָּם"
    },
    {
        "Word": "דָּבָֽר",
        "Shoresh": "דָּבָר"
    },
    {
        "Word": "דֹּֽדָתוֹ",
        "Shoresh": "דֹּד"
    },
    {
        "Word": "דֹּבֵר",
        "Shoresh": "דָּבַר"
    },
    {
        "Word": "דֶּבֶר",
        "Shoresh": "דֶּבֶר"
    },
    {
        "Word": "דַּבֶּר",
        "Shoresh": "דָּבַר"
    },
    {
        "Word": "דִּבֵּר",
        "Shoresh": "דָּבַר"
    },
    {
        "Word": "דִּבַּרְתֶּם",
        "Shoresh": "דָּבַר"
    },
    {
        "Word": "דִּבַּרְנוּ",
        "Shoresh": "דָּבַר"
    },
    {
        "Word": "דַּק",
        "Shoresh": "דָּקַק"
    },
    {
        "Word": "דָּמִֽים",
        "Shoresh": "דָּם"
    },
    {
        "Word": "דַֽם",
        "Shoresh": "דָּם"
    },
    {
        "Word": "דְּרוֹר",
        "Shoresh": "דְּרוֹר"
    },
    {
        "Word": "דָּק",
        "Shoresh": "דָּקַק"
    },
    {
        "Word": "דְּרָכֶךָ",
        "Shoresh": "דֶּ֫רֶךְ"
    },
    {
        "Word": "דָֽן",
        "Shoresh": "ארנבן"
    },
    {
        "Word": "דַיָּם",
        "Shoresh": "בְּדֵי"
    },
    {
        "Word": "דָּם",
        "Shoresh": "דָּם"
    },
    {
        "Word": "דָּמָהּ",
        "Shoresh": "דָּם"
    },
    {
        "Word": "דֵּי",
        "Shoresh": "דִּי"
    },
    {
        "Word": "דֹּד",
        "Shoresh": "דֹּד"
    },
    {
        "Word": "דָּרֹשׁ",
        "Shoresh": "דַּרְיוֹשׁ"
    },
    {
        "Word": "דָּרַשׁ",
        "Shoresh": "דָּרַשׁ"
    },
    {
        "Word": "דְּוֺתָהּ",
        "Shoresh": "דָּוָה"
    },
    {
        "Word": "דָּמֶיהָ",
        "Shoresh": "דָּם"
    },
    {
        "Word": "דַּל",
        "Shoresh": "דֶּלֶת"
    },
    {
        "Word": "דַּקָּה",
        "Shoresh": "דַּקָּה"
    },
    {
        "Word": "דָּמָם",
        "Shoresh": "דָּם"
    },
    {
        "Word": "דָּֽם",
        "Shoresh": "דָּם"
    },
    {
        "Word": "דֹּדָֽתְךָ",
        "Shoresh": "דֹּד"
    },
    {
        "Word": "דָל",
        "Shoresh": "דָּל"
    },
    {
        "Word": "דָּמָיו",
        "Shoresh": "דָּם"
    },
    {
        "Word": "דְּמֵיהֶם",
        "Shoresh": "דָּם"
    },
    {
        "Word": "דָּוָה",
        "Shoresh": "דָּוָה"
    },
    {
        "Word": "דֹּדָתוֹ",
        "Shoresh": "דֹּד"
    },
    {
        "Word": "דֹּדוֹ",
        "Shoresh": "דּוֹדוֹ"
    },
    {
        "Word": "דַק",
        "Shoresh": "דַּק"
    },
    {
        "Word": "דֹרֹֽתֵיכֶם",
        "Shoresh": "דּוֹר"
    },
    {
        "Word": "דִּבְרִי",
        "Shoresh": "דִּבְרִי"
    },
    {
        "Word": "דֹדוֹ",
        "Shoresh": "דּוֹד"
    },
    {
        "Word": "דַּיִשׁ",
        "Shoresh": "דַּיִשׁ"
    },
    {
        "Word": "דַּרְכֵיכֶֽם",
        "Shoresh": "דֶּ֫רֶךְ"
    },
    {
        "Word": "דֶבֶר",
        "Shoresh": "דֶּ֫בֶר"
    },
    {
        "Word": "דְּעוּאֵֽל",
        "Shoresh": "דְּעוּאֵל"
    },
    {
        "Word": "דִּגְלוֹ",
        "Shoresh": "דֶּ֫גֶל"
    },
    {
        "Word": "דֶּגֶל",
        "Shoresh": "דֶּגֶל"
    },
    {
        "Word": "דָכוּ",
        "Shoresh": "דּוּךְ"
    },
    {
        "Word": "דְבָרִי",
        "Shoresh": "דָּבָר"
    },
    {
        "Word": "דִבֵּר",
        "Shoresh": "דָּבַר"
    },
    {
        "Word": "דְבָרָי",
        "Shoresh": "דָּבָר"
    },
    {
        "Word": "דִּבַּת",
        "Shoresh": "דִּבָּה"
    },
    {
        "Word": "דִבָּה",
        "Shoresh": "דִּבָּה"
    },
    {
        "Word": "דִבַּת",
        "Shoresh": "דִּבָּה"
    },
    {
        "Word": "דָּתָן",
        "Shoresh": "דָּתָן"
    },
    {
        "Word": "דִבַּרְנוּ",
        "Shoresh": "דָּבַר"
    },
    {
        "Word": "דִּיבוֹן",
        "Shoresh": "דִּיבֹן"
    },
    {
        "Word": "דַּעַת",
        "Shoresh": "יָדַע"
    },
    {
        "Word": "דָּרַךְ",
        "Shoresh": "דָּרַךְ"
    },
    {
        "Word": "דָתָן",
        "Shoresh": "דָּתָן"
    },
    {
        "Word": "דֹּבְרֹת",
        "Shoresh": "דָּבַר"
    },
    {
        "Word": "דְּבָרוֹ",
        "Shoresh": "דָּבָר"
    },
    {
        "Word": "דֹּבֵֽר",
        "Shoresh": "דָּבַר"
    },
    {
        "Word": "דִּיבֹן",
        "Shoresh": "דִּיבֹן"
    },
    {
        "Word": "דִּבְלָתָֽיְמָה",
        "Shoresh": ""
    },
    {
        "Word": "דִּבְלָתָיְמָה",
        "Shoresh": ""
    },
    {
        "Word": "דִּמִּיתִי",
        "Shoresh": "דָּמָה"
    },
    {
        "Word": "דֹּבְרִֽים",
        "Shoresh": "דָּבַר"
    },
    {
        "Word": "דֹדֵיהֶן",
        "Shoresh": "דּוֹד"
    },
    {
        "Word": "דָּֽרַךְ",
        "Shoresh": "דָּרַךְ"
    },
    {
        "Word": "דְּלָתַיִם",
        "Shoresh": "דָּל"
    },
    {
        "Word": "דָּגָה",
        "Shoresh": "דָּגָה"
    },
    {
        "Word": "דַעַת",
        "Shoresh": "יָדַע"
    },
    {
        "Word": "דִּבֵּֽרוּ",
        "Shoresh": "דָּבַר"
    },
    {
        "Word": "דּֽוֹר",
        "Shoresh": "דּוֹר"
    },
    {
        "Word": "דְּגָנְךָ",
        "Shoresh": "דָּגָן"
    },
    {
        "Word": "דַּעְתִּי",
        "Shoresh": "יָדַע"
    },
    {
        "Word": "דְּרָכָיו",
        "Shoresh": "דֶּ֫רֶךְ"
    },
    {
        "Word": "דֹּרֵשׁ",
        "Shoresh": "דַּרְיוֹשׁ"
    },
    {
        "Word": "דְגָנֶךָ",
        "Shoresh": "דָּגָן"
    },
    {
        "Word": "דְּבָרַי",
        "Shoresh": "דָּבָר"
    },
    {
        "Word": "דְּגָֽנְךָ",
        "Shoresh": "דָּגָן"
    },
    {
        "Word": "דִּין",
        "Shoresh": "דִּין"
    },
    {
        "Word": "דְּגֽ͏ָנְךָ",
        "Shoresh": ""
    },
    {
        "Word": "דְבָרַי",
        "Shoresh": "דָּבָר"
    },
    {
        "Word": "דִבְּרוֹ",
        "Shoresh": "דָּבַר"
    },
    {
        "Word": "דִּבְּרוֹ",
        "Shoresh": "דָּבַר"
    },
    {
        "Word": "דְּרֹשׁ",
        "Shoresh": "דַּרְיוֹשׁ"
    },
    {
        "Word": "דַּכָּא",
        "Shoresh": "דַּכָּה"
    },
    {
        "Word": "דּוֹר",
        "Shoresh": "דּוֹר"
    },
    {
        "Word": "דָרֹשׁ",
        "Shoresh": "דָּרַשׁ"
    },
    {
        "Word": "דְרָכִים",
        "Shoresh": "דֶּ֫רֶךְ"
    },
    {
        "Word": "דְּרָכֶיךָ",
        "Shoresh": "דֶּ֫רֶךְ"
    },
    {
        "Word": "דִבְרֵי",
        "Shoresh": "דָּבָר"
    },
    {
        "Word": "דֶשֶׁא",
        "Shoresh": "דֶּ֫שֶׁא"
    },
    {
        "Word": "דְבַשׁ",
        "Shoresh": "דְּבַשׁ"
    },
    {
        "Word": "דוֹר",
        "Shoresh": "דּוֹר"
    },
    {
        "Word": "דַם",
        "Shoresh": "דָּם"
    },
    {
        "Word": "דָּבְאֶֽךָ",
        "Shoresh": "דֹּ֫בֶא"
    }
]